sqlalchemy_api/__about__.py
sqlalchemy_api/__init__.py
sqlalchemy_api/_types.py
sqlalchemy_api/actions.py
sqlalchemy_api/crud.py
sqlalchemy_api/exception_handlers.py
sqlalchemy_api/exceptions.py
sqlalchemy_api/filtering.py
sqlalchemy_api/pydantic_utils.py
sqlalchemy_api/responses.py
sqlalchemy_api/utils.py
sqlalchemy_api/adapters/__init__.py
sqlalchemy_api/adapters/fastapi_crud.py
sqlalchemy_api/adapters/starlette_crud.py
sqlalchemy_api-0.0.2.dist-info/METADATA
sqlalchemy_api-0.0.2.dist-info/WHEEL
sqlalchemy_api-0.0.2.dist-info/licenses/LICENSE.txt
sqlalchemy_api-0.0.2.dist-info/RECORD
