Metadata-Version: 2.1
Name: sqlalchemy-api
Version: 0.0.2
Project-URL: Documentation, https://github.com/nacosdev/sqlalchemy_api#readme
Project-URL: Issues, https://github.com/nacosdev/sqlalchemy-api/issues
Project-URL: Source, https://github.com/nacosdev/sqlalchemy-api
Author-email: Nicolas Acosta <nacosdev@gmail.com>
License-Expression: MIT
License-File: LICENSE.txt
Keywords: api,fastapi,rest,sqlalchemy,starlette
Classifier: Development Status :: 4 - Beta
Classifier: Programming Language :: Python
Classifier: Programming Language :: Python :: 3.7
Classifier: Programming Language :: Python :: 3.8
Classifier: Programming Language :: Python :: 3.9
Classifier: Programming Language :: Python :: 3.10
Classifier: Programming Language :: Python :: 3.11
Classifier: Programming Language :: Python :: Implementation :: CPython
Classifier: Programming Language :: Python :: Implementation :: PyPy
Requires-Python: >=3.7
Requires-Dist: psycopg2-binary>=2.9.5
Requires-Dist: pydantic>=2
Requires-Dist: sqlalchemy>=1.4
Provides-Extra: asgi
Requires-Dist: starlette; extra == 'asgi'
Requires-Dist: uvicorn; extra == 'asgi'
Provides-Extra: fastapi
Requires-Dist: fastapi>=0.100.0; extra == 'fastapi'
